{
  "_class": "text",
  "attributedString": {
    "_class": "attributedString",
    "attributes": [
      {
        "_class": "stringAttribute",
        "attributes": {
          "MSAttributedStringColorAttribute": {
            "_class": "color",
            "alpha": 1,
            "blue": 0.368627451,
            "green": 0.2862745098,
            "red": 0.2039215686
          },
          "MSAttributedStringFontAttribute": {
            "_class": "fontDescriptor",
            "attributes": {
              "name": "HiraginoSans-W5",
              "size": 12
            }
          },
          "kerning": 0.8100000023841858,
          "paragraphStyle": {
            "_class": "paragraphStyle",
            "alignment": 0,
            "baseWritingDirection": 0,
            "headerLevel": 1
          },
          "textStyleVerticalAlignmentKey": 0
        },
        "length": 7,
        "location": 0
      }
    ],
    "string": "取引量を決める"
  },
  "automaticallyDrawOnUnderlyingPath": false,
  "booleanOperation": -1,
  "clippingMaskMode": 0,
  "do_objectID": "7684CF65-9E00-4568-9109-C659AAFB1721",
  "dontSynchroniseWithSymbol": false,
  "exportOptions": {
    "_class": "exportOptions",
    "do_objectID": "AD45BE25-DCE1-4887-B3AC-3FE068F2CAFB",
    "exportFormats": [
    ],
    "includedLayerIds": [
    ],
    "layerOptions": 0,
    "shouldTrim": false
  },
  "frame": {
    "_class": "rect",
    "constrainProportions": false,
    "do_objectID": "5F21B8DD-74A3-47B4-8B35-CF22127C060E",
    "height": 12,
    "width": 100.0337837837836,
    "x": 16.67229729729726,
    "y": 0.6891891891891788
  },
  "glyphBounds": "{{0, 0}, {88, 12}}",
  "hasClippingMask": false,
  "isFixedToViewport": false,
  "isFlippedHorizontal": false,
  "isFlippedVertical": false,
  "isLocked": false,
  "isVisible": true,
  "layerListExpandedType": 0,
  "lineSpacingBehaviour": 2,
  "name": "取引量を決める",
  "nameIsFixed": false,
  "resizingConstraint": 47,
  "resizingType": 0,
  "rotation": 0,
  "shouldBreakMaskChain": false,
  "style": {
    "_class": "style",
    "do_objectID": "383FC32B-A58C-4717-B6CD-C0B60A4082A0",
    "endMarkerType": 0,
    "miterLimit": 10,
    "startMarkerType": 0,
    "textStyle": {
      "_class": "textStyle",
      "do_objectID": "F9A2E857-7674-44DC-BF2B-FCF308166072",
      "encodedAttributes": {
        "MSAttributedStringColorAttribute": {
          "_class": "color",
          "alpha": 1,
          "blue": 0.368627451,
          "green": 0.2862745098,
          "red": 0.2039215686
        },
        "MSAttributedStringFontAttribute": {
          "_class": "fontDescriptor",
          "attributes": {
            "name": "HiraginoSans-W5",
            "size": 12
          }
        },
        "kerning": 0.8100000023841858,
        "paragraphStyle": {
          "_class": "paragraphStyle",
          "alignment": 0,
          "baseWritingDirection": 0,
          "headerLevel": 1
        },
        "textStyleVerticalAlignmentKey": 0
      },
      "verticalAlignment": 0
    },
    "windingRule": 1
  },
  "textBehaviour": 1
}